gaus_bin_dist
