Metadata-Version: 2.1
Name: gaus-bin-dist
Version: 0.7
Summary: Gaussian and Binomial Distributions
Home-page: UNKNOWN
Author: Eric Kwok
Author-email: ekwok25@gmail.com
License: UNKNOWN
Platform: UNKNOWN
